docs/source/conf.py
pytonik/App.py
pytonik/Config.py
pytonik/Controllers.py
pytonik/Flash.py
pytonik/Hash.py
pytonik/Lang.py
pytonik/Log.py
pytonik/Model.py
pytonik/Request.py
pytonik/Router.py
pytonik/Session.py
pytonik/Version.py
pytonik/Web.py
pytonik/__init__.py
pytonik/__main__.py
pytonik/serv.py
pytonik/Core/File.py
pytonik/Core/Functions.py
pytonik/Core/Helpers.py
pytonik/Core/SMTP.py
pytonik/Core/__init__.py
pytonik/Core/env.py
pytonik/Core/requirement.py
pytonik/Driver/Schema.py
pytonik/Driver/__init__.py
pytonik/Driver/DB/__init__.py
pytonik/Driver/DB/MYSQL/MYSQL.py
pytonik/Driver/DB/MYSQL/Table.py
pytonik/Driver/DB/MYSQL/__init__.py
pytonik/Driver/DB/Oracle/Oracle.py
pytonik/Driver/DB/Oracle/Table.py
pytonik/Driver/DB/Oracle/__init__.py
pytonik/Driver/DB/SQLite/SQLite.py
pytonik/Driver/DB/SQLite/Table.py
pytonik/Driver/DB/SQLite/__init__.py
pytonik/Driver/DB/pyPgSQL/Table.py
pytonik/Driver/DB/pyPgSQL/__init__.py
pytonik/Driver/DB/pyPgSQL/pyPgSQL.py
pytonik/Editor/Compiler.py
pytonik/Editor/Node.py
pytonik/Editor/Resolver.py
pytonik/Editor/Template.py
pytonik/Editor/_Fragment.py
pytonik/Editor/__init__.py
pytonik/Functions/__.py
pytonik/Functions/__init__.py
pytonik/Functions/agent.py
pytonik/Functions/count.py
pytonik/Functions/curl.py
pytonik/Functions/extend.py
pytonik/Functions/include.py
pytonik/Functions/ip.py
pytonik/Functions/iteration.py
pytonik/Functions/now.py
pytonik/Functions/pagination.py
pytonik/Functions/path.py
pytonik/Functions/public.py
pytonik/Functions/rand.py
pytonik/Functions/readmore.py
pytonik/Functions/url.py
pytonik/Functions/validation.py
pytonik/cmd/__init__.py
pytonik/cmd/console.py
pytonik/cmd/doc.py
pytonik/cmd/help.py
pytonik/cmd/install.py
pytonik/cmd/land.zip
pytonik/cmd/lang.py
pytonik/cmd/server.py
pytonik/cmd/start.py
pytonik/cmd/errd/favicon.ico
pytonik/cmd/errd/index.html
pytonik/cmd/land/.env
pytonik/cmd/land/.htaccess
pytonik/cmd/land/LICENCE.txt
pytonik/cmd/land/app.log
pytonik/cmd/land/requirements.txt
pytonik-1.10.0.dist-info/LICENSE.txt
pytonik-1.10.0.dist-info/METADATA
pytonik-1.10.0.dist-info/WHEEL
pytonik-1.10.0.dist-info/entry_points.txt
pytonik-1.10.0.dist-info/top_level.txt
pytonik-1.10.0.dist-info/RECORD
