Metadata-Version: 2.1
Name: pytonik
Version: 1.10.0
Summary: Pytonik is a python framework built to enhance web development fast and easy, also help web developers to build more apps with less codes
Home-page: https://pytonik.com
Author: pytonik
Author-email: info@pytonik.com
Maintainer: Emmanuel Essien , Uduak Essien , Claret Nnamocha 
Maintainer-email: emmamartinscm@gmail.com , acushla4real@gmail.com , devclareo@gmail.com
License: GPL3
Keywords: mvc,oop,module,python,framework,web,app,pytonik,web,web development
Platform: UNKNOWN
Classifier: Environment :: Console
Classifier: Environment :: Web Environment
Classifier: Intended Audience :: Developers
Classifier: License :: OSI Approved :: BSD License
Classifier: Topic :: Office/Business
Classifier: Topic :: Internet :: WWW/HTTP :: Dynamic Content
Classifier: Topic :: Internet :: WWW/HTTP :: WSGI :: Application
Classifier: Topic :: Software Development :: Libraries :: Application Frameworks
Classifier: Topic :: Software Development :: Libraries :: Python Modules
Classifier: Operating System :: OS Independent
Classifier: Programming Language :: Python :: 2.7
Classifier: Programming Language :: Python :: 3
Classifier: Programming Language :: Python :: 3.4
Classifier: Programming Language :: Python :: 3.5
Classifier: Programming Language :: Python :: 3.6
Classifier: Programming Language :: Python :: 3.7
Classifier: Programming Language :: Python :: 3.8
Classifier: Programming Language :: Python :: 3.9
Classifier: Programming Language :: Python
Requires-Python: >=2.7, >=2.7.*, >=3.*
Requires-Dist: Pillow
Requires-Dist: colorama
Requires-Dist: mysql-connector-python
Requires-Dist: psycopg2-binary
Requires-Dist: cx-Oracle
